{
  "quote_id": "0b241b20f2a3_chunk_017",
  "text": "Den relativt osjälviska kärleken, vilken yttrar sig såsom beundran, tillgivenhet och deltagande Slutligen den helt osjälviska kärleken, som vill den älskades lycka, oberoende av egen lycka 3Självmedlidandet är krassaste, mest självförblindade slag av egoism Typiskt för denna självkärlek är, att den tror sig lida mer än de som den tillfogar lidande Det skulle innebära, att förföljelse och tortyr av andra vore raffinerat självplågeri 4Till egoistiska kärleken hör det speciella slags avund som kallas svartsjuka, en obotlig sjukdom (Oöverträffligt skarpt belyses detta tillstånd med Schleiermachers formulering: “Eifersucht ist eine Leidenschaft, die mit Eifer sucht was Leiden schafft",
  "source_book": "Unknown Series",
  "chapter": "l5_5",
  "language": "sv",
  "author": "Henry T. Laurency",
  "tradition": "Hylozoics",
  "verified": true,
  "metadata": {
    "file_path": "laurency_ultimate/swedish_Svenska/Books/Småskrifter/l5_5.pdf",
    "chunk_number": 17,
    "extraction_date": "2025-08-18T07:21:03.511407"
  }
}