{
  "quote_id": "1a965b451271_chunk_406",
  "text": "46 Die Moral 1Auch Russell hat betont, daß die Bezeichnungen Moral (vom Lateinischen) und Ethik (aus dem Griechischen), ursprünglich Sittenlehre, durch den Wortmißbrauch des Unwissens ihre eigentliche Bedeutung von Rechtsauffassung und Probleme des Zusammenlebens verloren haben 2Schopenhauer war der erste, der klarlegte, daß es noch keinem Philosophen gelungen war, die Moral zu einer Wissenschaft zu machen oder irgendwelche haltbaren Gründe für das Behaupten von absoluten oder objektiven Normen aufzustellen Sein Jünger Nietzsche ging einen Schritt weiter und erklärte, daß die überlieferten moralischen Betrachtungsweisen lebensuntauglich, um nicht zu sagen lebensfeindlich, wären",
  "source_book": "Unknown Series",
  "chapter": "KVger5",
  "language": "de",
  "author": "Henry T. Laurency",
  "tradition": "Hylozoics",
  "verified": true,
  "metadata": {
    "file_path": "laurency_ultimate/german_Deutsch/Books/Das Wissen um die Wirklichkeit/KVger5.pdf",
    "chunk_number": 406,
    "extraction_date": "2025-08-18T07:21:00.486105"
  }
}