{
  "quote_id": "1a965b451271_chunk_223",
  "text": "In diesem Fall suchen die Geschichtsforscher vergebens nach den ursprünglichen Einflüssen Entsprechend seiner Eigenart gibt jedermann den Ideen sein Gepräge Reif für diese sind auch nur die, welche ihnen selbständigen Ausdruck zu verleihen vermögen 17Als Eingeweihter hatte Goethe Wissen um gewisse grundlegende Tatsachen bekommen Z B hatte er Kenntnis von höheren Welten und davon, wie unmöglich es für einen Menschen mit alleiniger Auffassung von der sichtbaren Welt sein mußte, auf eigene Faust das Dasein erklären zu versuchen Er wußte auch, daß es zwischen dem Bewußtsein und der materiellen Wirklichkeit keine Kluft gibt, daß das Bewußtsein diese Wirklichkeit unmittelbar und unver- mittelt erlebt, daß Materie, Bewegung (Energie) und Bewußtsein verschiedene Seiten der- selben Sache sind",
  "source_book": "Unknown Series",
  "chapter": "KVger5",
  "language": "de",
  "author": "Henry T. Laurency",
  "tradition": "Hylozoics",
  "verified": true,
  "metadata": {
    "file_path": "laurency_ultimate/german_Deutsch/Books/Das Wissen um die Wirklichkeit/KVger5.pdf",
    "chunk_number": 223,
    "extraction_date": "2025-08-18T07:21:00.485685"
  }
}