{
  "quote_id": "1a965b451271_chunk_095",
  "text": "30Die selbständige Rechtsauffassung des Individuums zeigt sein erreichtes Entwicklungs- niveau und erworbenes Lebensverständnis 31Aristoteles ging davon aus, daß alles innerhalb der von den Lebensgesetzen bestimmten Grenzen gut ist Außerhalb des Gesetzes wird das Gute böse, werden die Tugenden Laster In der Lehre vom goldenen Mittelweg zwischen den Extremen (den „Gegensatzpaaren“ der Eso- terik) versuchte er jene Normen aufzustellen, welche der Mensch anwenden muß, um harmonisch und glücklich zu werden Laut Buddha ist dies der Weg der Weisheit 32„In allen Verhältnissen gibt es ein Zuviel und ein Zuwenig und ein richtiges Maß, welches mitten zwischen den beiden anderen liegt Es kann nicht mathematisch errechnet werden, aber die Vernunft lernt das rechte Maß durch die Erfahrung",
  "source_book": "Unknown Series",
  "chapter": "KVger5",
  "language": "de",
  "author": "Henry T. Laurency",
  "tradition": "Hylozoics",
  "verified": true,
  "metadata": {
    "file_path": "laurency_ultimate/german_Deutsch/Books/Das Wissen um die Wirklichkeit/KVger5.pdf",
    "chunk_number": 95,
    "extraction_date": "2025-08-18T07:21:00.485330"
  }
}