{
  "quote_id": "2844c43ce369_chunk_028",
  "text": "7Das Gemeinsame in allem sind hinsichtlich des Materieaspekts die beständigen Be- ziehungen (die Gesetze) und hinsichtlich des Bewußtseinsaspekts das sich stets erweiternde Kollektivbewußtsein 2 9 Telepathie 1Natürlich verleugnen und verhöhnen unsere gewaltigen, wissenschaftlich ausgebildeten Psychologen alles, was Telepathie heißt Es liegt nämlich außerhalb ihrer Fähigkeit, deren Existenz festzustellen 2Von den fünf Hüllen des Menschen, dem Organismus (Gehirn und Nervensystem), der physisch-ätherischen, der emotionalen, mentalen und kausalen Hülle, dienen vier (außer dem Organismus) als lebende Empfänger Sie bestehen nämlich aus Elementalmaterie mit passi- vem Bewußtsein",
  "source_book": "Unknown Series",
  "chapter": "KVger2",
  "language": "de",
  "author": "Henry T. Laurency",
  "tradition": "Hylozoics",
  "verified": true,
  "metadata": {
    "file_path": "laurency_ultimate/german_Deutsch/Books/Das Wissen um die Wirklichkeit/KVger2.pdf",
    "chunk_number": 28,
    "extraction_date": "2025-08-18T07:20:59.493643"
  }
}