{
  "quote_id": "2870c120c714_chunk_092",
  "text": "Den, som går den vägen, finner sin väg genom mörker och kaos Livet är arbete och möda i värld efter värld Liv är skapande frihet i glädjens arbete Daglig hängivenhet gör allting till fest, där det triviala dras upp till skönaste kultövning 405Sjung: “Jag älskar dig, o Herre, jag utgjuter mig för dig i vördnad och hängivenhet” Det ger eko långt upp i högre världar Genom hängivenhet, lojalitet, öppnas nya vägar till höjden, varifrån ljus och kraft komma Bli eld 406Räkna icke timmar, dagar och år, ty de äro sig lika för den som tjänar De äro lika glädjefyllda, lika sköna och härliga för den, som lever med högre världar för ögonen Den, som det kan i vardagslivets annars tröttsamma enahanda, har lärt sig en fundamental läxa i livet: att alltid vara lycklig och tacksam, där ödet placerat honom",
  "source_book": "Unknown Series",
  "chapter": "ekon",
  "language": "sv",
  "author": "Henry T. Laurency",
  "tradition": "Hylozoics",
  "verified": true,
  "metadata": {
    "file_path": "laurency_ultimate/swedish_Svenska/Books/Småskrifter/ekon.pdf",
    "chunk_number": 92,
    "extraction_date": "2025-08-18T07:21:03.348280"
  }
}