{
  "quote_id": "2fd9f70e5e4f_chunk_002",
  "text": "När människan faller i djup sömn, beror detta på att hennes emotionalhölje (med högre höljen) lämnat organism och eterhölje I vanliga fall stannar människan i sitt emotionalhölje någon meter från sin organism (med dess eterhölje) och förlorar sig i egna spekulationer och fantasier Hon är föga medveten om sin omgivning i emotionalvärlden, såvida hon icke blivit “väckt” till medvetenhet om denna, vilket förutsätter påverkan utifrån Vanligen kan hon tillse, att intet emotionalväsen får taga hennes organism i besittning Skulle detta på grund av bristande påpasslighet lyckas, inträder det tillstånd, som kallas “besatthet”, när rätte ägaren söker utdriva inkräktaren",
  "source_book": "Unknown Series",
  "chapter": "l3_9",
  "language": "sv",
  "author": "Henry T. Laurency",
  "tradition": "Hylozoics",
  "verified": true,
  "metadata": {
    "file_path": "laurency_ultimate/swedish_Svenska/Books/Livskunskap Tre/l3_9.pdf",
    "chunk_number": 2,
    "extraction_date": "2025-08-18T07:21:07.041634"
  }
}