{
  "quote_id": "4929eca02868_chunk_012",
  "text": "Så till exempel fortplantades första underrasen alltjämt genom knoppning och andra underrasen genom ägg, som utvecklades utan yttre befruktning Tredje underrasens individer var hermafroditer, hos vilka ettdera könet senare dominerade Först i fjärde underrasen delades könen Sedan dess har mänskliga individen varit enkönad och skall så förbli i denna klotperiod 10I tredje rotrasens tredje underras började övermänskliga väsen, andrajag, att inkarnera i mänskligheten Dessa var de så kallade urfäderna eller gudomliga androgynerna De hade till uppgift dels att leda och lära människorna, dels att förädla organism och högre höljen Dittills hade urfädernas ledning av släktet haft enbart fysisk betydelse",
  "source_book": "Unknown Series",
  "chapter": "fk12",
  "language": "sv",
  "author": "Henry T. Laurency",
  "tradition": "Hylozoics",
  "verified": true,
  "metadata": {
    "file_path": "laurency_ultimate/swedish_Svenska/Books/Förklaringen/fk12.pdf",
    "chunk_number": 12,
    "extraction_date": "2025-08-18T07:21:05.414697"
  }
}