{
  "quote_id": "72858f34ff37_chunk_031",
  "text": "Detta är en av förklaringarna varför de, som i barndomen inympats med vissa religiösa fiktioner och illusioner, aldrig kunna helt frigöra sig ifrån dessa Den religion, i vilken man är infödd, är enda och absoluta sanningen När skall folk börja inse det förnuftslösa i dylikt Att de finnas som övergå från en religion till en annan, har alltid förefallit dem, som kvarstått i den övergivna läran, som ofattbart, för att icke säga absurt Men förklaringen är enkel, när man väl är i besittning av universalnyckeln till alla mysterier 31Den, som under flera inkarnationer tillhört en och samma religion, kanske också särskilt bearbetat hithörande illusions- och fiktionssystem och därmed fått dem särskilt lätt återupplivade, känner sig oemotståndligt dragen till dessa ifall han ånyo påträffar dem",
  "source_book": "Unknown Series",
  "chapter": "l5_7",
  "language": "sv",
  "author": "Henry T. Laurency",
  "tradition": "Hylozoics",
  "verified": true,
  "metadata": {
    "file_path": "laurency_ultimate/swedish_Svenska/Books/Småskrifter/l5_7.pdf",
    "chunk_number": 31,
    "extraction_date": "2025-08-18T07:21:03.158763"
  }
}