{
  "quote_id": "8840887f5486_chunk_451",
  "text": "Det mentala deltagandet är det enda förnuftiga sättet att hjälpa, där hjälp kan givas 8Det folk anser vara mer eller mindre meningslöst lidande kan ha många olika uppgifter Det kan samtidigt vara avbetalning av gammal skuld, medföra frigörelse från icke önskvärda egen- skaper, nyttig lärdom (erforderlig läxa), aningslöst genomgånget prov, nödvändig härdning Lidandet är oundvikligt i den mån det är tillmätt skörd av dålig sådd Men dels kunna vi med vårt förnuft avsevärt minska lidandet, dels har det sina kompensationer Det frigör och avslöjar, förädlar och höjer, fördjupar och klargör, väcker förmåga av förståelse och deltagande Lidandet utvecklar egenskaper som tålamod, självbehärskning, oberördhet, uthållighet, hjältemod Ingen kan få lida oförskyllt Liv är icke lidande",
  "source_book": "Unknown Series",
  "chapter": "l1_9",
  "language": "sv",
  "author": "Henry T. Laurency",
  "tradition": "Hylozoics",
  "verified": true,
  "metadata": {
    "file_path": "laurency_ultimate/swedish_Svenska/Books/Livskunskap Ett/l1_9.pdf",
    "chunk_number": 451,
    "extraction_date": "2025-08-18T07:21:01.155034"
  }
}