{
  "quote_id": "8840887f5486_chunk_103",
  "text": "Han lever då utan möjlighet till friktion med andra i full harmoni Han tillämpar enhetens lag och lever därför automatiskt i överensstämmelse med Lagen, enär enhetens lag är sammanfattning av alla livslagar i självförverkligandet 4Enligt frihetslagen har varje individ rätt till den frihet (betingad av insikt och förmåga) han en gång förvärvat och i fortsättningen lagenligt tillämpar Misstag ifråga om frihetslagen medför inskränkning av möjlighet till frihet Den inskränkningen kan visa sig i olika avseenden: för med- vetenhetsutvecklingen otjänliga höljen, otjänlig miljö, otjänliga sociala och kulturella förhållanden Konstateras kan detta faktum endast genom studium av hundratals föregående inkarnationer",
  "source_book": "Unknown Series",
  "chapter": "l1_9",
  "language": "sv",
  "author": "Henry T. Laurency",
  "tradition": "Hylozoics",
  "verified": true,
  "metadata": {
    "file_path": "laurency_ultimate/swedish_Svenska/Books/Livskunskap Ett/l1_9.pdf",
    "chunk_number": 103,
    "extraction_date": "2025-08-18T07:21:01.154014"
  }
}