{
  "quote_id": "b79ecf4f8e1c_chunk_083",
  "text": "4Den intellektuella utbildningens resultat, omdömesförmågan, är ej större än att man dagligen 15 kan träffa på människor, som veta allting bättre om sådant de icke veta något alls De ha icke lärt sig skilja på vad de veta och icke veta, aldrig frågat sig: vad har jag för fakta för det Någon har sagt De ha läst Och sen veta de 5Sokrates’ stora insats för mer än två tusen år sedan var att han försökte få människorna inse, att de ”ingenting visste” (om verkligheten) Den insikten är första förutsättningen för esoteriken Den som tror sig kunna bedöma, tror sig vara vis, är olämplig för esoteriken Jättarna inom exote- riska forskningen skulle vara ännu större, om de kunde inse sin ohjälpliga begränsning Då skulle Einstein icke ha varit så säker på sina slutsatser om relativiteten",
  "source_book": "Unknown Series",
  "chapter": "l1_7",
  "language": "sv",
  "author": "Henry T. Laurency",
  "tradition": "Hylozoics",
  "verified": true,
  "metadata": {
    "file_path": "laurency_ultimate/swedish_Svenska/Books/Livskunskap Ett/l1_7.pdf",
    "chunk_number": 83,
    "extraction_date": "2025-08-18T07:21:02.429360"
  }
}