{
  "quote_id": "e4645adc48d5_chunk_091",
  "text": "Aber es hat die Möglichkeit, mehr oder weniger rasch zu erfahren, was es wissen will, unabhängig von Raum und vergangener Zeit in der angegebenen Welt alle Beziehungen der drei Aspekte (Materie, Bewegung, Bewußtsein) in dieser Welt festzustellen 1 31 Die „Wiedergeburt“ von allem 1Alle materiellen Formen (Atome, Moleküle, Aggregate, Welten, Planeten, Sonnensysteme, Aggregate von Sonnensystemen usw ) sind dem Gesetz der Verwandlung unterworfen Sie werden geformt, verändert, aufgelöst und aufs neue geformt Dies ist unvermeidlich, weil keine materiellen Formen auf die Dauer dem Verschleiß durch kosmische Energien stand- halten können 2Die Uratome, welche alle diese Gebilde zusammensetzen, bekommen dadurch Gelegen- heiten, immer neue Erfahrungen in neuen Formen zu machen Alle lernen durch alles",
  "source_book": "Unknown Series",
  "chapter": "KVger1",
  "language": "de",
  "author": "Henry T. Laurency",
  "tradition": "Hylozoics",
  "verified": true,
  "metadata": {
    "file_path": "laurency_ultimate/german_Deutsch/Books/Das Wissen um die Wirklichkeit/KVger1.pdf",
    "chunk_number": 91,
    "extraction_date": "2025-08-18T07:20:59.328791"
  }
}