{
  "quote_id": "f8c6100d185c_chunk_042",
  "text": "Alla är både subjekt och objekt 7Ännu ett exempel “Kunskap” uppfattas av principtänkandet absolut: rätt uppfattning av verkligheten Men när vi studerar hur kunskap fungerar konkret, inser vi att den är en relationssak och inget absolut Kunskap är en relation mellan den uppfattande och den verklighet som kunskapen har till föremål, men inte vilken relation som helst utan relationen av korrekt uppfattning Återigen är “korrekt uppfattning” inget absolut Olika subjekt, olika människor har olika förmåga till uppfattning Det finns för envar en övre gräns för förståelse, en gräns som är olika för alla Det som är kunskap för en människa är det inte för en annan Det hon inte begriper blir ingen kunskap för henne, det hon missuppfattar blir motsatsen till kunskap (fiktion) för henne",
  "source_book": "Unknown Series",
  "chapter": "fk10",
  "language": "sv",
  "author": "Henry T. Laurency",
  "tradition": "Hylozoics",
  "verified": true,
  "metadata": {
    "file_path": "laurency_ultimate/swedish_Svenska/Books/Förklaringen/fk10.pdf",
    "chunk_number": 42,
    "extraction_date": "2025-08-18T07:21:05.259793"
  }
}