{
  "quote_id": "1a965b451271_chunk_392",
  "text": "Es war eine ebenso furchtbare wie berechtigte Anklage, welche Goethe gegen die scheinbar unheilbare Abgestumpftheit schleuderte: „Es erben sich Gesetz und Rechte wie eine ew’ge Krankheit fort “ Und Tegnér könnte hinzufügen: „Nur die Barbarei war einst vaterländisch “ Das kann man von allen Nationen sagen 4Natürlich mußte ein Kulturvertreter von Russells Kaliber vieles von der in unserer vielrenommierten Zivilisation noch übrigen Barbarei entdecken Umso heftiger waren seine Angriffe auf die Indolenz, die Trägheit, die Feigheit, den Unwillen zu Erneuerungen, deren Notwendigkeit klar auf der Hand lag 5Die bedauerliche Folge dieses lebensblinden Egoismus ist, daß die Reformideen der Idealisten von unzuständigen Demagogen aufgegriffen worden sind",
  "source_book": "Unknown Series",
  "chapter": "KVger5",
  "language": "de",
  "author": "Henry T. Laurency",
  "tradition": "Hylozoics",
  "verified": true,
  "metadata": {
    "file_path": "laurency_ultimate/german_Deutsch/Books/Das Wissen um die Wirklichkeit/KVger5.pdf",
    "chunk_number": 392,
    "extraction_date": "2025-08-18T07:21:00.486078"
  }
}