{
  "quote_id": "1edfa836156c_chunk_038",
  "text": "Också planeter och solsystem är aggregat, levande former 2Aggregaten av materieslagen 43–48 tillhör involutionen Dessa livsformer kallas elementaler och har passiv medvetenhet Exempel är människans höljen av överfysisk materia 3Aggregaten av fysisk materia, 49, tillhör evolutionen Dessa livsformer, till exempel mineral, växt-, djur- och människoorganismer samt dessas eterhöljen, har en svag aktiv medvetenhet Den visar sig bland annat i deras förmåga till självformning och ändamålsenlig anpassning till omvärlden 4Involutionens elementaler har ingen möjlighet till självaktiv medvetenhet Men under påverkan utifrån blir de ofelbart aktiverade 5Genom sina olika riken lär sig elementalerna att uppta alla vibrationer de träffas av och återge dessa förstärkta",
  "source_book": "Unknown Series",
  "chapter": "fk4",
  "language": "sv",
  "author": "Henry T. Laurency",
  "tradition": "Hylozoics",
  "verified": true,
  "metadata": {
    "file_path": "laurency_ultimate/swedish_Svenska/Books/Förklaringen/fk4.pdf",
    "chunk_number": 38,
    "extraction_date": "2025-08-18T07:21:06.629728"
  }
}