{
  "quote_id": "27d7923b4858_chunk_025",
  "text": "4 Yogiernas världar 1Enligt esoteriken ha de individer, som uppnått femte naturriket och ingått i planethierarkien, de fyra planetariska atomvärldarna 46–49 till sitt förfogande Individerna i fjärde naturriket leva i tre atomvärldar (47–49), uppdelade i fem molekylarvärldar 2Vissa yogaskolor tala om de fem kosmiska världarna Andra nöja sig med tre världar i universum 3De som tro att kosmos har fem världar, bevilja även jaget fem höljen eller åtminstone fyra, ifall det femte och högsta är den allt omfattande världssjälen Brahman Somliga tycka att det kan räcka med tre, och definitionerna påminna i sin oklarhet om teologernas kropp, själ och ande 4Vissa yogaförfattare tala under hänvisning till Patanjali om fem olika slag av medvetenhet hos individen",
  "source_book": "Unknown Series",
  "chapter": "kv7",
  "language": "sv",
  "author": "Henry T. Laurency",
  "tradition": "Hylozoics",
  "verified": true,
  "metadata": {
    "file_path": "laurency_ultimate/swedish_Svenska/Books/Kunskapen om verkligheten/kv7.pdf",
    "chunk_number": 25,
    "extraction_date": "2025-08-18T07:21:04.298739"
  }
}