{
  "quote_id": "27d7923b4858_chunk_134",
  "text": "23 Slutord 1Människan har alla de egenskaper och förmågor hon förvärvat genom alla inkarnationer Men dessa förbli latenta (begravda) i undermedvetenheten, tills de ånyo aktualiseras och aktiveras i ny inkarnation Hon har alltifrån barbarstadiet förvärvat alla mänsklighetens goda och dåliga egenskaper, alla till några procent Egenskaperna på lägre nivåer kallas dåliga, de på högre goda Procenttalet bestämmer effektiviteten Tillfällen till aktualisering och aktivering i ny inkarnation väcka egenskaperna till liv Ofta räcker det med återerinring Därav alla uppfostrares och kulturapostlars ansvar (Ansvar kan betyda, att man själv i kommande liv icke får tillfälle till eller direkt hämmas i sin utveckling eller rentav idiotiseras",
  "source_book": "Unknown Series",
  "chapter": "kv7",
  "language": "sv",
  "author": "Henry T. Laurency",
  "tradition": "Hylozoics",
  "verified": true,
  "metadata": {
    "file_path": "laurency_ultimate/swedish_Svenska/Books/Kunskapen om verkligheten/kv7.pdf",
    "chunk_number": 134,
    "extraction_date": "2025-08-18T07:21:04.299031"
  }
}