{
  "quote_id": "2844c43ce369_chunk_047",
  "text": "Erfreulicherweise können wir erwarten, daß jene Individuen, welche in Chaldäa solche Einsichten erworben hatten, wieder inkarnieren werden, um der Menschheit aufs neue die esoterische „Astrologie“ zu schenken, wodurch sie das seit langem vergessene Wissen wiederaufleben lassen werden Sie werden von der planetaren Hierarchie die erforderlichen Tatsachen erhalten, was ihr latentes Wissen zu neuem Leben wecken wird Dies ist, was ständig geschieht und ist in Übereinstimmung mit dem GESETZ Was der Mensch ausführen kann, muß er selbst tun Es ist Sache der Menschheit, sich an verlorenes Wissen wiederzuerinnern 12Und damit sind wir bei der von den Astronomen als gröbste Form des Aberglaubens be- 12 trachteten Astrologie",
  "source_book": "Unknown Series",
  "chapter": "KVger2",
  "language": "de",
  "author": "Henry T. Laurency",
  "tradition": "Hylozoics",
  "verified": true,
  "metadata": {
    "file_path": "laurency_ultimate/german_Deutsch/Books/Das Wissen um die Wirklichkeit/KVger2.pdf",
    "chunk_number": 47,
    "extraction_date": "2025-08-18T07:20:59.493689"
  }
}