{
  "quote_id": "2870c120c714_chunk_132",
  "text": "573En upphöjt självförnekande tanke ändrar även i fysiskt avseende en persons aura, tillför kroppen välgörande materia 574Rosendoft är med sällhet närbesläktad doft Icke utan orsak var rosen alkemisternas mysteriesymbol Våra dagars rosenolja är underhaltig 575Tillit förbereder kunskap Tillit intensifierar energien Ifall energispänningen är åtföljd av glädje, är kraften äkta 576Förtvivlan, misströstan, fruktan är all tillits död, all kunskaps död De, som uppleva hierarkiens sällhet, kunna icke förtvivla Det är första tecknet på nyttan av högre kunskap 577Man måste vänja sig vid att vara i ständig förbindelse med hierarkien Det är fågelns trygga näste i människans hjärta Hjärtat måste ha något att hänga fast vid: om icke högre ting, så guld eller mat och dryck",
  "source_book": "Unknown Series",
  "chapter": "ekon",
  "language": "sv",
  "author": "Henry T. Laurency",
  "tradition": "Hylozoics",
  "verified": true,
  "metadata": {
    "file_path": "laurency_ultimate/swedish_Svenska/Books/Småskrifter/ekon.pdf",
    "chunk_number": 132,
    "extraction_date": "2025-08-18T07:21:03.348424"
  }
}