{
  "quote_id": "30f942c110d6_chunk_079",
  "text": "26Platon utgick ifrån att kausala insiktens idévärld är slutmålet för mänskliga medvetenhetsutvecklingen och kallade den såsom högsta uppnåeliga utvecklingsstadiet för människan såsom människa för ”det sant varande” Uttrycket ogillades av Aristoteles, som antydde, att det ”sant varande” är homogena urmaterien (i vilken otaliga kosmoi formas och upplösas, sedan ändamålet förverkligats) När Aristoteles skulle på sitt realistiska sätt omskriva det Platon kallat ideernas hierarki, försökte han visa, hur allt högre former voro möjliga genom att högre potentiellt förefanns i lägre Hans förfaringssätt därvid har tydligen aldrig förståtts av hans lärjungar Och så fick man i stället hela denna procedur med form och materia, verkligt och möjligt, som sysselsatte särskilt skolastikerna",
  "source_book": "Unknown Series",
  "chapter": "kv5",
  "language": "sv",
  "author": "Henry T. Laurency",
  "tradition": "Hylozoics",
  "verified": true,
  "metadata": {
    "file_path": "laurency_ultimate/swedish_Svenska/Books/Kunskapen om verkligheten/kv5.pdf",
    "chunk_number": 79,
    "extraction_date": "2025-08-18T07:21:04.068259"
  }
}