{
  "quote_id": "3f13eb398d71_chunk_003",
  "text": ") och ”Till folket talade han endast i liknelser” Det är endast sådant, som finns kvar av Jeshu ord Ty folket idag är detsamma som folket då Vad Jeshu i övrigt sade finns ej i evangelierna Det finns hos gnostikerna i deras ännu icke publicerade referat av Jeshu ord Evangelierna äro skrivna för folket och innehålla inga ”guds rikes hemligheter” eller esoteriska kunskapen 5Alltsedan Atlantis gick under, har den så missbrukade kunskapen om verkligheten varit förbehållen dem som förvärvat rätt att få del av den Det var med mycket stor tvekan, som man lät den bli offentlig efter år 1875 Endast två 45-jag röstade vid konklaven år 1775 för, alla övriga ledamöterna mot Men planethärskaren resolverade, ”eftersom dessa två våra bröder vilja taga följderna på sig, så må de få göra detta offer",
  "source_book": "Unknown Series",
  "chapter": "l1_3",
  "language": "sv",
  "author": "Henry T. Laurency",
  "tradition": "Hylozoics",
  "verified": true,
  "metadata": {
    "file_path": "laurency_ultimate/swedish_Svenska/Books/Livskunskap Ett/l1_3.pdf",
    "chunk_number": 3,
    "extraction_date": "2025-08-18T07:21:01.641172"
  }
}