{
  "quote_id": "46f3b167fc95_chunk_004",
  "text": "3Kristus såg gudomen uppenbarad överallt och i allt För honom var livet och allt i livet gudomligt till sitt väsen Det finns ingenting av kristendomens pessimistiska livssyn i hans livsuppfattning Det onda är relativ ofullkomlighet och beror på okunnighet och oförmåga Utvecklingen avhjälper okunnigheten och självförverkligandet oförmågan 4Kristus förkunnade enda sanna religionen Det finns blott en religion Alla avatarer, budbärare från gudarnas riken, ha i alla tider förkunnat samma sanningar Sanningen är en, kunskapen om verkligheten och livet Individens delkunskap och uppfattning av denna beror av hans utvecklingsnivå 5Alla avatarernas läror ha blivit förfalskade Deras olika framställningar av kunskapen måste anpassas efter rådande föreställningssätt och allmänna uppfattningsmöjligheten",
  "source_book": "Unknown Series",
  "chapter": "l5_6",
  "language": "sv",
  "author": "Henry T. Laurency",
  "tradition": "Hylozoics",
  "verified": true,
  "metadata": {
    "file_path": "laurency_ultimate/swedish_Svenska/Books/Småskrifter/l5_6.pdf",
    "chunk_number": 4,
    "extraction_date": "2025-08-18T07:21:02.997419"
  }
}