{
  "quote_id": "4929eca02868_chunk_041",
  "text": "De känner solsystemets alla lagar och tillämpar dem med fulländad precision Detta är “allmakt”, om än av lägsta grad Därför är tredjejagen det lägsta slag av jag som kallas gudomsjag 10Detta innebär, att vår planethierarki har en “överkapacitet”, om uttrycket tillåts Alla dess funktioner i de fyra lägre naturrikena skulle egentligen kunna fullgöras av enbart andrajag, om normala förhållanden rådde på vår planet Men det är just vad det inte gör med vår näst intill urspårade mänsklighet, med allvarliga brott mot livslagarna även i lägre riken (djurs rovliv och växters parasitliv ) Att även tredjejag ingår i hierarkin och att planetregeringen finns som en ännu mäktigare instans, är yttersta garantin för det godas slutliga seger på vårt klot",
  "source_book": "Unknown Series",
  "chapter": "fk12",
  "language": "sv",
  "author": "Henry T. Laurency",
  "tradition": "Hylozoics",
  "verified": true,
  "metadata": {
    "file_path": "laurency_ultimate/swedish_Svenska/Books/Förklaringen/fk12.pdf",
    "chunk_number": 41,
    "extraction_date": "2025-08-18T07:21:05.414780"
  }
}