{
  "quote_id": "4929eca02868_chunk_003",
  "text": "5För monadens totala manifestation åtgår många planetsystem, som regel ett per elementalrike eller naturrike Vi, som är människor i nuvarande Tellus-systemet, har alltså varit djur i föregående planetkedjan De medväsen, som nu är djur, var växter i det föregående 6Också själva planeternas fysiska, emotionala och mentala etc materia (inklusive monadernas höljen) är till stor del ärvd från det äldre systemet Detta har medfört, att vårt system redan vid sin tillkomst hade vissa förvärvade egenskaper, som underlättat materieformningen och därmed indirekt främjat medvetenhetsutvecklingen Exempel på sådana egenskaper är cellernas förmåga av självgestaltning samt frö- och äggbildningen Detta ger också svaret på frågan, “Var den första hönan höna eller var hon ägg",
  "source_book": "Unknown Series",
  "chapter": "fk12",
  "language": "sv",
  "author": "Henry T. Laurency",
  "tradition": "Hylozoics",
  "verified": true,
  "metadata": {
    "file_path": "laurency_ultimate/swedish_Svenska/Books/Förklaringen/fk12.pdf",
    "chunk_number": 3,
    "extraction_date": "2025-08-18T07:21:05.414669"
  }
}