{
  "quote_id": "4aff3ba0a053_chunk_028",
  "text": "När den insikten blivit axiomatisk hos mänskligheten i stort, har människan uppnått 5 myndighetsåldern, icke förr 10Lag och rätt är ett problem, som filosoferna ännu icke kunnat utreda Ifall man med lag menar rättslagstiftningen, så har den långt kvar, innan begreppen rätt och orätt blivit utredda Man kan rentav säga, att rätt börjar där lag slutar När mänskligheten lärt sig inse, att allt är hat som icke är kärlek, börjar den fatta vad som är ”rätt” 11Det goda är kärlek, det onda är hat 12Det goda har naturligtvis ingenting med sentimentalitet att göra, med oförmågan att säga nej 13Bland de många förfalskningar av Jeshu ord, som förekomma i gnostikernas evangelieromaner, finns ingen mera vilseledande än den, att man icke bör stå det onda emot",
  "source_book": "Unknown Series",
  "chapter": "l1_8",
  "language": "sv",
  "author": "Henry T. Laurency",
  "tradition": "Hylozoics",
  "verified": true,
  "metadata": {
    "file_path": "laurency_ultimate/swedish_Svenska/Books/Livskunskap Ett/l1_8.pdf",
    "chunk_number": 28,
    "extraction_date": "2025-08-18T07:21:00.842555"
  }
}