{
  "quote_id": "56f1eeaf5cbb_chunk_028",
  "text": "Automatiskt falla de in i sina rätta sammanhang och ge verklighetsinnehåll åt det skenbart meningslösa Esoterikern får lära sig att ”vandra i mörker”, att ingenting förstå Det är också en läxa som ger insikt Det komiska därvid är att alla andra äro så mycket mera säkra på och vissa om allt Han ensam är ”dåren” 6 4 Mänsklighetens frigörelse 1Medvetenhetsprocessen, expansionsprocessen, kan man förlikna vid en frigörelse från begränsningar Därav ockulta talet om ”andarna i fängelset” Där det finns gränser av något slag, där kraftfältet (verkningssfären) är kringskuret, där kontaktens radie är begränsad, där är medvetenhetens fängelse Överallt, där det finns något att införliva med medvetenheten, ser denna sin begränsning och driver livsinstinkten att erövra",
  "source_book": "Unknown Series",
  "chapter": "l1_6",
  "language": "sv",
  "author": "Henry T. Laurency",
  "tradition": "Hylozoics",
  "verified": true,
  "metadata": {
    "file_path": "laurency_ultimate/swedish_Svenska/Books/Livskunskap Ett/l1_6.pdf",
    "chunk_number": 28,
    "extraction_date": "2025-08-18T07:21:02.583442"
  }
}