{
  "quote_id": "56f1eeaf5cbb_chunk_035",
  "text": "När han lärt allt han behöver lära för att kunna undvara höljet, blir detta ett hinder, om individen icke frigör sig från beroendet En esoterisk pedagog måste lära sig inse, när lärjungen är mogen för de olika frigörelserna, och icke för tidigt och i varje fall aldrig med tvång söka framtvinga frigörelsen 3Esoteriska läraren får icke framtvinga frigörelsen från känslorna, så länge lärjungen behöver dessa för att känna sig leva, förrän lärjungen förvärvat erforderliga attraktionens egenskaper och eliminerat alla repellerande Läraren får icke lära eleven frigöra sig från intellektuella behov, förr- 6 än lärjungen utvecklat sina mentala förmågor Det är ett stort misstag att förakta det lägre, innan detta bemästrats och blivit överflödigt",
  "source_book": "Unknown Series",
  "chapter": "l1_6",
  "language": "sv",
  "author": "Henry T. Laurency",
  "tradition": "Hylozoics",
  "verified": true,
  "metadata": {
    "file_path": "laurency_ultimate/swedish_Svenska/Books/Livskunskap Ett/l1_6.pdf",
    "chunk_number": 35,
    "extraction_date": "2025-08-18T07:21:02.583462"
  }
}