{
  "quote_id": "7ceabbd32b2c_chunk_027",
  "text": "Men den inre, den subjektiva medvetenheten, såsom känslor, tankar och ideer, är lika absolut och något eget, som inte kan sättas lika med objektiva fenomen som kemiska och elektriska processer i nervcellerna Materialismen är i sin ensidighet ohållbar 6Den så kallade idealismen inom filosofin har däremot bortsett från materieaspekten och hävdat, att den objektiva verkligheten skulle vara enbart subjektiv upplevelse Slutsatsen av detta synsätt blir helt absurd: att allt materiellt enbart är illusion 7Inom fysiken hävdar man numera, att “allt är energi” Enligt hylozoiken är energi detsamma som materia i rörelse Det återstår för vetenskapen att upptäcka medvetenheten i denna dynamiska materia, upptäcka medvetenhetens universella existens",
  "source_book": "Unknown Series",
  "chapter": "fk1",
  "language": "sv",
  "author": "Henry T. Laurency",
  "tradition": "Hylozoics",
  "verified": true,
  "metadata": {
    "file_path": "laurency_ultimate/swedish_Svenska/Books/Förklaringen/fk1.pdf",
    "chunk_number": 27,
    "extraction_date": "2025-08-18T07:21:06.343979"
  }
}