{
  "quote_id": "8840887f5486_chunk_164",
  "text": "Att teologerna alltsedan Atlantis framställt ”gudomen” såsom dömande, visar vad de äro för ”andas barn” Kyrkofadern Eusebios’ förvrängningar av Jeshu ord visa, hur alltigenom otillförlitliga nya testamentets skrifter äro Den som har kunskap om Lagen, kan också själv utmönstra lögnerna Därtill behövs ingen teologi, denna parodi på sunt förnuft 9 28 Tjänande 1Alla utgöra en enhet (delägare i kosmiska totalmedvetenheten), alla äro bröder Men det betyder icke, att alla befinna sig på samma utvecklingsstadium Utvecklingen består av en sken- bart oändlig serie utvecklingsnivåer Det demokratiska kravet på ”jämlikhet” strider mot livets lag 2Även om vi befinna oss på olika utvecklingsstadier, så äro vi alla på vägen, om vi veta om det eller ej, alla i samma rike",
  "source_book": "Unknown Series",
  "chapter": "l1_9",
  "language": "sv",
  "author": "Henry T. Laurency",
  "tradition": "Hylozoics",
  "verified": true,
  "metadata": {
    "file_path": "laurency_ultimate/swedish_Svenska/Books/Livskunskap Ett/l1_9.pdf",
    "chunk_number": 164,
    "extraction_date": "2025-08-18T07:21:01.154186"
  }
}