{
  "quote_id": "a5b480635f56_chunk_082",
  "text": "Dabei ist 15 jedoch zu beachten, dass sich die von den Satanisten gegründeten Gesellschaften als viel lebensfähiger erweisen werden als die Theosophische Gesellschaft, die auf Initiative der planetaren Hierarchie gegründet und von den Schülern Blavatsky, Besant und Leadbeater in den Jahren 1875–1920 gefördert wurde Der Grund für dieses Scheitern ist, dass diese Gesellschaft nicht mehr den Rückhalt der planetaren Hierarchie hat, und deshalb ist sie stagniert",
  "source_book": "Unknown Series",
  "chapter": "L3D18",
  "language": "de",
  "author": "Henry T. Laurency",
  "tradition": "Hylozoics",
  "verified": true,
  "metadata": {
    "file_path": "laurency_ultimate/german_Deutsch/Books/Lebenskenntnis Drei/L3D18.pdf",
    "chunk_number": 82,
    "extraction_date": "2025-08-18T07:20:59.132671"
  }
}