{
  "quote_id": "b79ecf4f8e1c_chunk_112",
  "text": "Hamna de i en miljö, vars världs- och livsåskådning äro olika deras latenta verklighets- och livsuppfattning, i en idiotiserande omgivning utan kontakter, bli de totalt desorienterade, känna icke igen sig och bli desperata eller åtminstone antikonventionella 2Esoteriska barn ha det i regel svårare i skolan än andra Det som läres går i regel emot deras livsinstinkt och synes dem främmande och olustigt, varför de i regel förlora intresset för allt vad studier heter De känna sig såsom främlingar, bli i regel missförstådda av både lärare och kamrater och betraktas såsom särlingar, vilket ytterligare försvårar livet under uppväxtåren De kanske aldrig eller ”för sent vakna”, uppnå sin latenta nivå",
  "source_book": "Unknown Series",
  "chapter": "l1_7",
  "language": "sv",
  "author": "Henry T. Laurency",
  "tradition": "Hylozoics",
  "verified": true,
  "metadata": {
    "file_path": "laurency_ultimate/swedish_Svenska/Books/Livskunskap Ett/l1_7.pdf",
    "chunk_number": 112,
    "extraction_date": "2025-08-18T07:21:02.429435"
  }
}