{
  "quote_id": "c51892c9747e_chunk_003",
  "text": "4Denna sunda skepsis är önskvärd även därför, att esoteriska sekter finnas, som icke härröra från individer anslutna till planethierarkien Som alltid har svarta logen, när den ej kunnat hindra utbredningen av esoteriska vetandet, vilket den i det längsta försökt, låtit inrätta egna samfund (även efterapat gamla beteckningar), som också ståta med ”mästare” förvillande lika planethier- arkiens i sitt framställningssätt Svarta logen arbetar också mycket mer intensivt, vilket antyddes med uttrycket ”världens barn äro visare än ljusets barn”, en antydan som naturligtvis misstolkats av de lärde 5Det finns många olika slag och grader av lärjungaskap till planethierarkien En gång antagen för alltid antagen Men det betyder icke, att man alltid vet något därom",
  "source_book": "Unknown Series",
  "chapter": "l1_4",
  "language": "sv",
  "author": "Henry T. Laurency",
  "tradition": "Hylozoics",
  "verified": true,
  "metadata": {
    "file_path": "laurency_ultimate/swedish_Svenska/Books/Livskunskap Ett/l1_4.pdf",
    "chunk_number": 3,
    "extraction_date": "2025-08-18T07:21:02.020852"
  }
}