{
  "quote_id": "de82d6b2c89e_chunk_031",
  "text": "Att emotionalvärlden intresserar devahierarkien och de olika laginstanserna, är även en helt annan sak Planethierarkien leder medvetenhetsutvecklingen, ingenting annat 26När mänskligheten förvärvat kunskap om verkligheten och nått mentalstadiet, upplösas formerna i emotionalvärlden, som då uppvisar enbart oformad materia 10 6 Livet mellan inkarnationerna i mentalvärlden 1Sedan individens emotionalhölje upplösts, fortsätter jagmedvetenheten att i mentalhöljet leva ett absolut subjektivt liv utan möjlighet till objektiv medvetenhet i mentalvärlden Det hela uppleves med förnimmelse av intensiv realitet, och det faller honom därför aldrig ett ögonblick in, att alltsammans är fantasifoster Någon svag föreställning om detta få vi någon gång i våra drömmar",
  "source_book": "Unknown Series",
  "chapter": "l3_10",
  "language": "sv",
  "author": "Henry T. Laurency",
  "tradition": "Hylozoics",
  "verified": true,
  "metadata": {
    "file_path": "laurency_ultimate/swedish_Svenska/Books/Livskunskap Tre/l3_10.pdf",
    "chunk_number": 31,
    "extraction_date": "2025-08-18T07:21:07.364487"
  }
}