{
  "quote_id": "f8c6100d185c_chunk_041",
  "text": "inte kan separeras utan är den medvetna, dynamiska materiens “sätt att vara till” Lika litet kan man separera “orsak” och “verkan” i verkligheten Om man vid bedömningen av ett visst skeende ensidigt uppfattar vissa krafter och energier som “orsaker” och andra som “verkningar”, måste man snart revidera sin syn Ty de “orsakande” energierna kan inte undgå att påverkas av förhållandena de påverkar, och så uppstår i själva verket ett system av sammansatt växelverkan 6Motsvarande gäller uppfattningen av subjekt och objekt i exempelvis psykologi och pedagogik Perspektivtänkandet ser inte läraren som undervisningens blotta subjekt och eleven som dess blotta objekt Läraren lär själv genom att undervisa och gör det genom sina elever Gör han inte det, är han inte längre lärare",
  "source_book": "Unknown Series",
  "chapter": "fk10",
  "language": "sv",
  "author": "Henry T. Laurency",
  "tradition": "Hylozoics",
  "verified": true,
  "metadata": {
    "file_path": "laurency_ultimate/swedish_Svenska/Books/Förklaringen/fk10.pdf",
    "chunk_number": 41,
    "extraction_date": "2025-08-18T07:21:05.259790"
  }
}